dos.py
sztestlib/__init__.py
sztestlib/szlibone.py
xiaoriben-1.0.0.dist-info/LICENSE.txt
xiaoriben-1.0.0.dist-info/METADATA
xiaoriben-1.0.0.dist-info/WHEEL
xiaoriben-1.0.0.dist-info/top_level.txt
xiaoriben-1.0.0.dist-info/RECORD
