Metadata-Version: 2.1
Name: xiaoriben
Version: 1.0.0
Summary: this is a niubi lib
Home-page: http://upload.pypi.org/legacy/
Author: Sz
Author-email: 651757088@qq.com
License: MIT
Platform: UNKNOWN
